LICENSE
MANIFEST.in
README.md
pyproject.toml
requirements.txt
setup.cfg
setup.py
classifyhub/__init__.py
classifyhub/predict.py
classifyhub.egg-info/PKG-INFO
classifyhub.egg-info/SOURCES.txt
classifyhub.egg-info/dependency_links.txt
classifyhub.egg-info/requires.txt
classifyhub.egg-info/top_level.txt
classifyhub/libhub/__init__.py
classifyhub/libhub/timm_models.py
classifyhub/utils/__init__.py
classifyhub/utils/data_utils.py
classifyhub/utils/file_utils.py